.git
.gitignore
Dockerfile
LICENSE
NOTICE
README.md
Vagrantfile
contributors.txt
etherflow_acitoolkit/__about__.py
etherflow_acitoolkit/__init__.py
etherflow_acitoolkit/aciConcreteLib.py
etherflow_acitoolkit/aciFaults.py
etherflow_acitoolkit/aciHealthScore.py
etherflow_acitoolkit/aciSearch.py
etherflow_acitoolkit/aciTable.py
etherflow_acitoolkit/acibaseobject.py
etherflow_acitoolkit/acicounters.py
etherflow_acitoolkit/acifakeapic.py
etherflow_acitoolkit/aciphysobject.py
etherflow_acitoolkit/acisession.py
etherflow_acitoolkit/acitoolkitlib.py
etherflow_acitoolkit/etherflow_acitoolkit.py
poetry.lock
pylintrc
pyproject.toml
requirements.txt
setup.py
shippable.yml
etherflow_acitoolkit-0.4.7.dist-info/LICENSE
etherflow_acitoolkit-0.4.7.dist-info/METADATA
etherflow_acitoolkit-0.4.7.dist-info/NOTICE
etherflow_acitoolkit-0.4.7.dist-info/WHEEL
etherflow_acitoolkit-0.4.7.dist-info/RECORD
